statsplot/__init__.py
statsplot/_version.py
statsplot/dimred.py
statsplot/example_iris.py
statsplot/plot.py
statsplot/siglabels.py
statsplot/stats.py
statsplot/statstable.py
statsplot/transformations.py
statsplot-2.3.3.dist-info/LICENSE.txt
statsplot-2.3.3.dist-info/METADATA
statsplot-2.3.3.dist-info/WHEEL
statsplot-2.3.3.dist-info/top_level.txt
statsplot-2.3.3.dist-info/RECORD
