Metadata-Version: 2.1
Name: statsplot
Version: 2.3.3
Summary: A package for most important plot for (biological)-sciences
Home-page: https://github.com/silask/statsplot
Author: Silas Kieser
License: MIT
Keywords: plotting
License-File: LICENSE.txt
